{"nodes": [{"id": "mono_audio_recording", "label": "Mono Audio Recording (voice preference)", "file_type": "document", "source_file": "raw/slack/eclipse/channels/app-team/2026/02/2026-02-20__app-team.md", "source_location": null, "source_url": null, "captured_at": null, "author": null, "contributor": null}, {"id": "privacy_policy", "label": "Privacy Policy & Financial Incentive Notice", "file_type": "document", "source_file": "raw/slack/eclipse/channels/app-team/2026/02/2026-02-20__app-team.md", "source_location": null, "source_url": null, "captured_at": null, "author": null, "contributor": null}], "edges": [{"source": "julien", "target": "mono_audio_recording", "relation": "implements", "confidence": "EXTRACTED", "confidence_score": 1.0, "source_file": "raw/slack/eclipse/channels/app-team/2026/02/2026-02-20__app-team.md", "source_location": null, "weight": 1.0}, {"source": "alac_format", "target": "mono_audio_recording", "relation": "conceptually_related_to", "confidence": "INFERRED", "confidence_score": 0.7, "source_file": "raw/slack/eclipse/channels/app-team/2026/02/2026-02-20__app-team.md", "source_location": null, "weight": 1.0}, {"source": "sydney", "target": "privacy_policy", "relation": "discusses", "confidence": "EXTRACTED", "confidence_score": 1.0, "source_file": "raw/slack/eclipse/channels/app-team/2026/02/2026-02-20__app-team.md", "source_location": null, "weight": 1.0}], "hyperedges": []}