{"nodes": [{"id": "vapi-ai", "label": "Vapi.ai", "file_type": "document", "source_file": "raw/slack/eclipse/channels/app-team/2026/03/2026-03-10__app-team.md", "source_location": null, "source_url": null, "captured_at": null, "author": null, "contributor": null}, {"id": "fomo-family", "label": "Fomo Family", "file_type": "document", "source_file": "raw/slack/eclipse/channels/app-team/2026/03/2026-03-10__app-team.md", "source_location": null, "source_url": null, "captured_at": null, "author": null, "contributor": null}, {"id": "v1-app-release", "label": "OkBoomer / HumanAPI v1 App Store Release", "file_type": "document", "source_file": "raw/slack/eclipse/channels/app-team/2026/03/2026-03-10__app-team.md", "source_location": null, "source_url": null, "captured_at": null, "author": null, "contributor": null}, {"id": "thehumanapi-com", "label": "thehumanapi.com (landing page)", "file_type": "document", "source_file": "raw/slack/eclipse/channels/app-team/2026/03/2026-03-10__app-team.md", "source_location": null, "source_url": null, "captured_at": null, "author": null, "contributor": null}], "edges": [{"source": "v1-app-release", "target": "okboomer", "relation": "references", "confidence": "EXTRACTED", "confidence_score": 1.0, "source_file": "raw/slack/eclipse/channels/app-team/2026/03/2026-03-10__app-team.md", "source_location": null, "weight": 1.0}, {"source": "v1-app-release", "target": "humanapi-app", "relation": "references", "confidence": "EXTRACTED", "confidence_score": 1.0, "source_file": "raw/slack/eclipse/channels/app-team/2026/03/2026-03-10__app-team.md", "source_location": null, "weight": 1.0}, {"source": "daniel", "target": "v1-app-release", "relation": "implements", "confidence": "EXTRACTED", "confidence_score": 1.0, "source_file": "raw/slack/eclipse/channels/app-team/2026/03/2026-03-10__app-team.md", "source_location": null, "weight": 1.0}, {"source": "vj", "target": "thehumanapi-com", "relation": "implements", "confidence": "EXTRACTED", "confidence_score": 1.0, "source_file": "raw/slack/eclipse/channels/app-team/2026/03/2026-03-10__app-team.md", "source_location": null, "weight": 1.0}, {"source": "thehumanapi-com", "target": "fomo-family", "relation": "references", "confidence": "EXTRACTED", "confidence_score": 1.0, "source_file": "raw/slack/eclipse/channels/app-team/2026/03/2026-03-10__app-team.md", "source_location": null, "weight": 1.0}, {"source": "adithya-shak-kumar", "target": "vapi-ai", "relation": "works_with", "confidence": "EXTRACTED", "confidence_score": 1.0, "source_file": "raw/slack/eclipse/channels/app-team/2026/03/2026-03-10__app-team.md", "source_location": null, "weight": 1.0}], "hyperedges": []}