{"nodes": [{"id": "durgi_uncle_bay_area", "label": "Durgi Uncle (Bay Area)", "file_type": "document", "source_file": "raw/imessage/individuals/durgi-uncle-bay-area/2026/2026-03__durgi-uncle-bay-area.md", "source_location": null, "source_url": null, "captured_at": null, "author": null, "contributor": null}], "edges": [{"source": "durgi_uncle_bay_area", "target": "adithya", "relation": "messages_with", "confidence": "EXTRACTED", "confidence_score": 1.0, "source_file": "raw/imessage/individuals/durgi-uncle-bay-area/2026/2026-03__durgi-uncle-bay-area.md", "source_location": null, "weight": 1.0}, {"source": "durgi_uncle_bay_area", "target": "san_francisco", "relation": "lives_in", "confidence": "INFERRED", "confidence_score": 0.8, "source_file": "raw/imessage/individuals/durgi-uncle-bay-area/2026/2026-03__durgi-uncle-bay-area.md", "source_location": null, "weight": 0.8}, {"source": "adithya", "target": "nvidia_gtc", "relation": "co_attended", "confidence": "EXTRACTED", "confidence_score": 1.0, "source_file": "raw/imessage/individuals/durgi-uncle-bay-area/2026/2026-03__durgi-uncle-bay-area.md", "source_location": null, "weight": 1.0}], "hyperedges": []}