{"nodes": [{"id": "synps", "label": "Synps / Synapse", "file_type": "document", "source_file": "raw/imessage/individuals/ryan-ut-austin/2025/2025-08__ryan-ut-austin.md", "source_location": null, "source_url": null, "captured_at": null, "author": null, "contributor": null}], "edges": [{"source": "adithya", "target": "synps", "relation": "works_at", "confidence": "EXTRACTED", "confidence_score": 1.0, "source_file": "raw/imessage/individuals/ryan-ut-austin/2025/2025-08__ryan-ut-austin.md", "source_location": null, "weight": 1.0}], "hyperedges": []}