{"nodes": [], "edges": [{"source": "ryan_ogren", "target": "adithya", "relation": "messages_with", "confidence": "EXTRACTED", "confidence_score": 1.0, "source_file": "raw/imessage/_profiles/group-group-ryan-tyler.md", "source_location": null, "weight": 1.0}, {"source": "ryan_ogren", "target": "tyler_sheppard", "relation": "discussed_with", "confidence": "EXTRACTED", "confidence_score": 1.0, "source_file": "raw/imessage/_profiles/group-group-ryan-tyler.md", "source_location": null, "weight": 1.0}], "hyperedges": []}