{"nodes": [], "edges": [{"source": "tyler_sheppard_la", "target": "adithya", "relation": "messages_with", "confidence": "EXTRACTED", "confidence_score": 1.0, "source_file": "raw/imessage/_profiles/group-group-donny-tyler-yosef.md", "source_location": null, "weight": 1.0}, {"source": "yosef_producer_la", "target": "adithya", "relation": "messages_with", "confidence": "EXTRACTED", "confidence_score": 1.0, "source_file": "raw/imessage/_profiles/group-group-donny-tyler-yosef.md", "source_location": null, "weight": 1.0}, {"source": "yosef_producer_la", "target": "music_production", "relation": "works_at", "confidence": "INFERRED", "confidence_score": 0.85, "source_file": "raw/imessage/_profiles/group-group-donny-tyler-yosef.md", "source_location": null, "weight": 0.9}], "hyperedges": [{"id": "la_music_producers", "label": "LA Music Producer Circle", "members": ["donny_producer_la", "yosef_producer_la", "tyler_sheppard_la", "malik_producer_la"], "relation": "co_attended", "source_file": "raw/imessage/_profiles/group-group-donny-tyler-yosef.md", "confidence": "INFERRED", "confidence_score": 0.8}]}