{"nodes": [{"id": "group_mom_3", "label": "Group: Mom + Unknown (3)", "file_type": "document", "source_file": "raw/imessage/_profiles/group-group-mom-3.md", "source_location": null, "source_url": null, "captured_at": null, "author": null, "contributor": null}], "edges": [{"source": "group_mom_3", "target": "adithya", "relation": "messages_with", "confidence": "EXTRACTED", "confidence_score": 1.0, "source_file": "raw/imessage/_profiles/group-group-mom-3.md", "source_location": null, "weight": 1.0}], "hyperedges": []}