{"nodes": [{"id": "anjali_hinge_austin", "label": "Anjali Nagarajan (Hinge Austin)", "file_type": "document", "source_file": "raw/imessage/individuals/anjali-hinge-austin/2026/2026-03__anjali-hinge-austin.md", "source_location": null, "source_url": null, "captured_at": null, "author": null, "contributor": null}], "edges": [{"source": "anjali_hinge_austin", "target": "adithya", "relation": "messages_with", "confidence": "EXTRACTED", "confidence_score": 1.0, "source_file": "raw/imessage/individuals/anjali-hinge-austin/2026/2026-03__anjali-hinge-austin.md", "source_location": null, "weight": 1.0}, {"source": "anjali_hinge_austin", "target": "zilker_park_austin", "relation": "mentioned_by", "confidence": "EXTRACTED", "confidence_score": 1.0, "source_file": "raw/imessage/individuals/anjali-hinge-austin/2026/2026-03__anjali-hinge-austin.md", "source_location": null, "weight": 0.8}], "hyperedges": []}