{"nodes": [], "edges": [{"source": "yosef", "target": "adithya", "relation": "messages_with", "confidence": "EXTRACTED", "confidence_score": 1.0, "source_file": "raw/imessage/groups/group-donny-yosef/2025/2025-09__group-donny-yosef.md", "source_location": null, "weight": 1.0}, {"source": "donny_darkpop", "target": "yosef", "relation": "co_attended", "confidence": "EXTRACTED", "confidence_score": 1.0, "source_file": "raw/imessage/groups/group-donny-yosef/2025/2025-09__group-donny-yosef.md", "source_location": null, "weight": 1.0}], "hyperedges": []}