{"nodes": [], "edges": [{"source": "perla_renter_showing", "target": "adithya", "relation": "messages_with", "confidence": "EXTRACTED", "confidence_score": 1.0, "source_file": "raw/imessage/individuals/perla-renter-showing/2025/2025-08__perla-renter-showing.md", "source_location": null, "weight": 1.0}, {"source": "perla_renter_showing", "target": "klein_street_property", "relation": "related_to", "confidence": "EXTRACTED", "confidence_score": 1.0, "source_file": "raw/imessage/individuals/perla-renter-showing/2025/2025-08__perla-renter-showing.md", "source_location": null, "weight": 1.0}], "hyperedges": []}