{"nodes": [{"id": "akshar_usc_nyc", "label": "Akshar (USC, NYC)", "file_type": "document", "source_file": "raw/imessage/individuals/akshar-usc-nyc/2025/2025-07__akshar-usc-nyc.md", "source_location": null, "source_url": null, "captured_at": null, "author": null, "contributor": null}], "edges": [{"source": "akshar_usc_nyc", "target": "adithya", "relation": "messages_with", "confidence": "EXTRACTED", "confidence_score": 1.0, "source_file": "raw/imessage/individuals/akshar-usc-nyc/2025/2025-07__akshar-usc-nyc.md", "source_location": null, "weight": 1.0}, {"source": "akshar_usc_nyc", "target": "new_york_city", "relation": "lives_in", "confidence": "EXTRACTED", "confidence_score": 1.0, "source_file": "raw/imessage/individuals/akshar-usc-nyc/2025/2025-07__akshar-usc-nyc.md", "source_location": null, "weight": 1.0}], "hyperedges": []}